Workbook
Name offer_01_benefits_level_02: 'Summarize Your Offer'!$K$17:$L$38
Name offer_01_terms_header: 'Summarize Your Offer'!$N$17:$P$19
Name offer_02_benefits_variable: 'Summarize Your 2nd Offer'!$E$17:$F$22
Name offer_02_terms: 'Summarize Your 2nd Offer'!$N$21:$P$27
Name offer_02_benefits_level_02: 'Summarize Your 2nd Offer'!$K$17:$L$38
Name offer_01_benefits_equity: 'Summarize Your Offer'!$E$26:$F$31
Name offer_01_terms: 'Summarize Your Offer'!$N$21:$P$27
Name offer_02_benefits_level_01: 'Summarize Your 2nd Offer'!$H$17:$I$31
Name offer_01_benefits_variable: 'Summarize Your Offer'!$E$17:$F$22
Name offer_02_terms_header: 'Summarize Your 2nd Offer'!$N$17:$P$19
Name offer_02_benefits_equity: 'Summarize Your 2nd Offer'!$E$26:$F$31
Name offer_01_benefits_level_01: 'Summarize Your Offer'!$H$17:$I$31

Sheet Summarize Your Offer
R3: Copy Tool
B8: Summarize Your Offer
B11: Trying to decide if you should accept a job offer? Unsure if you should accept, negotiate or decline? Use this tool to help you understand your full offer and whether or not it's a good fit for your next job. Complete the offer summary tab by inputting your offer details below. Fill out the yellow cells and check the boxes from the checklists.
B15: Cash | E15: Variable | H15: Benefits - Level 1 | K15: Benefits - Level 2 | N15: Terms
B17: Gross Offer | E17: FALSE | F17: Performance Bonuses | H17: TRUE | I17: Health Insurance | K17: TRUE | L17: Work From Home | N17: Job Title: | P17: Marketing Director
B18: Input your annual gross salary only | E18: TRUE | F18: Commission | H18: TRUE | I18: Dental Insurance | K18: TRUE | L18: Modified Hours | N18: Reporting to: | P18: VP, Marketing
B19: Annual | C19: 100000 | E19: TRUE | F19: Hiring Bonus | H19: TRUE | I19: Vision Insurance | K19: FALSE | L19: Tuition Reimbursement | N19: Start Date: | P19: 44044
B20: Monthly | C20: =C19/12 -> 8333.3333 | E20: FALSE | F20: Profit Sharing | H20: FALSE | I20: Disability Insurance | K20: FALSE | L20: Childcare Costs
E21: TRUE | F21: Other Example | H21: FALSE | I21: Life Insurance | K21: FALSE | L21: Relocation | N21: TRUE | O21: Non-Compete
B22: Net Offer | E22: FALSE | H22: TRUE | I22: 401K | K22: FALSE | L22: Transportation Costs | N22: FALSE | O22: Severance
B23: Calculate your annual net salary only (you can adjust pay frequency on the left side menu) | H23: FALSE | I23: 401K Matching | K23: FALSE | L23: Meals | N23: TRUE | O23: Intellectual Property
E24: Equity | H24: FALSE | I24: Vacation PTO | K24: TRUE | L24: Gym Membership | N24: FALSE
H25: TRUE | I25: Sick PTO | K25: FALSE | L25: Cell Phone Reimbursement | N25: FALSE
B26: Annual | C26: 66905 | E26: FALSE | F26: Stock | H26: TRUE | I26: Parental Leave | K26: FALSE | L26: Expense Account | N26: FALSE
B27: Monthly | C27: =C26/12 -> 5575.4167 | E27: TRUE | F27: Options | H27: FALSE | K27: TRUE | L27: Sabaticals | N27: FALSE
E28: FALSE | F28: RSUs | H28: FALSE | K28: FALSE | L28: Software Training
E29: FALSE | F29: Vesting | H29: FALSE | K29: FALSE | L29: On-the-job Training
E30: FALSE | H30: FALSE | K30: FALSE | L30: Conferences / Seminars
E31: FALSE | H31: FALSE | K31: FALSE | L31: Professional Memberships
K32: FALSE | L32: Licensure
K33: TRUE | L33: Certifications
K34: FALSE | L34: Hardware
K35: FALSE | L35: Internet Reimbursement
K36: FALSE | L36: Company Car
K37: TRUE | L37: HSA / FSA
K38: FALSE | L38: First Class Travel

Sheet Analyze Your Offer
B8: Analyze Your Offer
B11: Now it's time to look at the cash offered against your expenses and savings goals. Complete the offer analysis tab by inputting your monthly expenses, monthly desired savings, and your current savings in the yellow cells below
B15: Cash Offered | E15: Projected Expenses & Savings | H15: Cash Runway | K15: Offer Analysis
B17: Gross Offer | E17: Projected Expenses | H17: Your Savings | K17: Projected Expenses vs Cash Offered | N17: Desired Savings vs Cash Offered
E18: Calculate your monthly expenses only | H18: Input your current savings only
B19: Annual | C19: ='Summarize Your Offer'!C19 -> 100000 | E19: Annual | F19: =F20*12 -> 60000 | H19: Savings | I19: 15000 | K19: Monthly expenses | N19: Monthly savings
B20: Monthly | C20: ='Summarize Your Offer'!C20 -> 8333.3333 | E20: Monthly | F20: 5000 | H20: Budget | I20: =F20 -> 5000 | K20: Offer Net | L20: =C25 -> 5575.4167 | N20: Offer Savings | O20: =L22 -> 575.41667
H21: Runway | I21: =CONCATENATE((I19/I20)," ","months") -> 3 months | K21: Budget | L21: =F20 -> 5000 | N21: Desired Savings | O21: =F25 -> 1000
B22: Net Offer | E22: Desired Savings | K22: $ left after expenses | L22: =L20-L21 -> 575.41667 | N22: $ left after expenses & savings | O22: =O20-O21 -> -424.58333
E23: Input your monthly desired savings only
B24: Annual | C24: ='Summarize Your Offer'!C26 -> 66905 | E24: Annual | F24: =F25*12 -> 12000
B25: Monthly | C25: ='Summarize Your Offer'!C27 -> 5575.4167 | E25: Monthly | F25: 1000 | K25: Annual expenses | N25: Annual savings
K26: Offer Net | L26: =C24 -> 66905 | N26: Offer Savings | O26: =L28 -> 6905
K27: Budget | L27: =F19 -> 60000 | N27: Desired Savings | O27: =F24 -> 12000
K28: $ left after expenses | L28: =L26-L27 -> 6905 | N28: $ left after expenses & savings | O28: =O26-O27 -> -5095

Sheet Summarize Your 2nd Offer
R3: Copy Tool
B8: Summarize Your Offer
B11: Trying to decide if you should accept a job offer? Unsure if you should accept, negotiate or decline? Use this tool to help you understand your full offer and whether or not it's a good fit for your next job. Complete the offer summary tab by inputting your offer details below. Fill out the yellow cells and check the boxes from the checklists.
B15: Cash | E15: Variable | H15: Benefits - Level 1 | K15: Benefits - Level 2 | N15: Terms
B17: Gross Offer | E17: FALSE | F17: Performance Bonuses | H17: TRUE | I17: Health Insurance | K17: FALSE | L17: Work From Home | N17: Job Title: | P17: Sr. Marketing Director
B18: Input your annual gross salary only | E18: TRUE | F18: Commission | H18: FALSE | I18: Dental Insurance | K18: FALSE | L18: Modified Hours | N18: Reporting to: | P18: CMO
B19: Annual | C19: 125000 | E19: FALSE | F19: Hiring Bonus | H19: FALSE | I19: Vision Insurance | K19: FALSE | L19: Tuition Reimbursement | N19: Start Date: | P19: 44044
B20: Monthly | C20: =C19/12 -> 10416.667 | E20: FALSE | F20: Profit Sharing | H20: FALSE | I20: Disability Insurance | K20: FALSE | L20: Childcare Costs
E21: FALSE | H21: TRUE | I21: Life Insurance | K21: FALSE | L21: Relocation | N21: TRUE | O21: Non-Compete
B22: Net Offer | E22: FALSE | H22: TRUE | I22: 401K | K22: FALSE | L22: Transportation Costs | N22: TRUE | O22: Severance
B23: Calculate your annual net salary only | H23: FALSE | I23: 401K Matching | K23: TRUE | L23: Meals | N23: FALSE | O23: Intellectual Property
B24: Annual | C24: 81068 | E24: Equity | H24: FALSE | I24: Vacation PTO | K24: FALSE | L24: Gym Membership | N24: FALSE
B25: Monthly | C25: =C24/12 -> 6755.6667 | H25: TRUE | I25: Sick PTO | K25: TRUE | L25: Cell Phone Reimbursement | N25: FALSE
E26: TRUE | F26: Stock | H26: TRUE | I26: Parental Leave | K26: FALSE | L26: Expense Account | N26: FALSE
E27: FALSE | F27: Options | H27: FALSE | K27: FALSE | L27: Sabaticals | N27: FALSE
E28: FALSE | F28: RSUs | H28: FALSE | K28: TRUE | L28: Software Training
E29: FALSE | F29: Vesting | H29: FALSE | K29: FALSE | L29: On-the-job Training
E30: FALSE | H30: FALSE | K30: FALSE | L30: Conferences / Seminars
E31: FALSE | H31: FALSE | K31: FALSE | L31: Professional Memberships
K32: FALSE | L32: Licensure
K33: FALSE | L33: Certifications
K34: FALSE | L34: Hardware
K35: FALSE | L35: Internet Reimbursement
K36: FALSE | L36: Company Car
K37: FALSE | L37: HSA / FSA
K38: FALSE | L38: First Class Travel

Sheet Analyze Your 2nd Offer
B8: Analyze Your Offer
B11: Now it's time to look at the cash offered against your expenses and savings goals. This offer analysis tab will autopopulate based on your inputs on earlier tabs. No need to enter anything here
B15: Cash Offered | E15: Projected Expenses & Savings | H15: Cash Runway | K15: Offer Analysis
B17: Gross Offer | E17: Projected Expenses | H17: Your Savings | K17: Projected Expenses vs Cash Offered | N17: Desired Savings vs Cash Offered
B19: Annual | C19: ='Summarize Your 2nd Offer'!C19 -> 125000 | E19: Annual | F19: ='Analyze Your Offer'!F19 -> 60000 | H19: Savings | I19: ='Analyze Your Offer'!I19 -> 15000 | K19: Monthly expenses | N19: Monthly savings
B20: Monthly | C20: ='Summarize Your 2nd Offer'!C20 -> 10416.667 | E20: Monthly | F20: ='Analyze Your Offer'!F20 -> 5000 | H20: Budget | I20: ='Analyze Your Offer'!I20 -> 5000 | K20: Offer Net | L20: =C25 -> 6755.6667 | N20: Offer Savings | O20: =L22 -> 1755.6667
H21: Runway | I21: ='Analyze Your Offer'!I21 -> 3 months | K21: Budget | L21: =F20 -> 5000 | N21: Desired Savings | O21: =F25 -> 1000
B22: Net Offer | E22: Desired Savings | K22: $ left after expenses | L22: =L20-L21 -> 1755.6667 | N22: $ left after expenses & savings | O22: =O20-O21 -> 755.66667
B24: Annual | C24: ='Summarize Your 2nd Offer'!C24 -> 81068 | E24: Annual | F24: ='Analyze Your Offer'!F24 -> 12000
B25: Monthly | C25: ='Summarize Your 2nd Offer'!C25 -> 6755.6667 | E25: Monthly | F25: ='Analyze Your Offer'!F25 -> 1000 | K25: Annual expenses | N25: Annual savings
K26: Offer Net | L26: =C24 -> 81068 | N26: Offer Savings | O26: =L28 -> 21068
K27: Budget | L27: =F19 -> 60000 | N27: Desired Savings | O27: =F24 -> 12000
K28: $ left after expenses | L28: =L26-L27 -> 21068 | N28: $ left after expenses & savings | O28: =O26-O27 -> 9068

Sheet Compare Your Offers
B8: Compare Your Offers
B11: If you are debating between 2 offers it might be helpful to compare them side by side. This offer comparison tab will autopopulate based on previous tabs. Please only complete the career values by following the instructions below. Any benefits that are unique to 1 offer with be bolded in green text.
D15: Offer 1 | L15: Offer 2
B17: CASH | D17: Projected Expenses vs Cash Offered | G17: Desired Savings vs Cash Offered | L17: Projected Expenses vs Cash Offered | O17: Desired Savings vs Cash Offered
D19: Monthly expenses | G19: Monthly savings | L19: Monthly expenses | O19: Monthly savings
D20: Offer Net | E20: ='Analyze Your Offer'!L20 -> 5575.4167 | G20: Offer Savings | H20: ='Analyze Your Offer'!O20 -> 575.41667 | L20: Offer Net | M20: ='Analyze Your 2nd Offer'!L20 -> 6755.6667 | O20: Offer Savings | P20: ='Analyze Your 2nd Offer'!O20 -> 1755.6667
D21: Budget | E21: ='Analyze Your Offer'!L21 -> 5000 | G21: Desired Savings | H21: ='Analyze Your Offer'!O21 -> 1000 | L21: Budget | M21: ='Analyze Your 2nd Offer'!L21 -> 5000 | O21: Desired Savings | P21: ='Analyze Your 2nd Offer'!O21 -> 1000
D22: $ left after expenses | E22: =E20-E21 -> 575.41667 | G22: $ left after expenses & savings | H22: =H20-H21 -> -424.58333 | L22: $ left after expenses | M22: =M20-M21 -> 1755.6667 | O22: $ left after expenses & savings | P22: =P20-P21 -> 755.66667
D25: Annual expenses | G25: Annual savings | L25: Annual expenses | O25: Annual savings
D26: Offer Net | E26: ='Analyze Your Offer'!L26 -> 66905 | G26: Offer Savings | H26: ='Analyze Your Offer'!O26 -> 6905 | L26: Offer Net | M26: ='Analyze Your 2nd Offer'!L26 -> 81068 | O26: Offer Savings | P26: ='Analyze Your 2nd Offer'!O26 -> 21068
D27: Budget | E27: ='Analyze Your Offer'!L27 -> 60000 | G27: Desired Savings | H27: ='Analyze Your Offer'!O27 -> 12000 | L27: Budget | M27: ='Analyze Your 2nd Offer'!L27 -> 60000 | O27: Desired Savings | P27: ='Analyze Your 2nd Offer'!O27 -> 12000
D28: $ left after expenses | E28: =E26-E27 -> 6905 | G28: $ left after expenses & savings | H28: =H26-H27 -> -5095 | L28: $ left after expenses | M28: =M26-M27 -> 21068 | O28: $ left after expenses & savings | P28: =P26-P27 -> 9068
B31: EMPLOYMENT TERMS & VALUES | D31: Employment Terms | G31: Career Values | L31: Employment Terms | O31: Career Values
D32: {=INDEX(offer_01_terms_header,0,1)} -> Job Title: | E32: {=INDEX(offer_01_terms_header,0,3)} -> Marketing Director | G32: Review your Career Values & Intentions Select your top 3 values from the drop down and confirm whether or not this offer "checks the box" | L32: {=INDEX(offer_02_terms_header,0,1)} -> Job Title: | M32: {=INDEX(offer_02_terms_header,0,3)} -> Sr. Marketing Director | O32: Review your Career Values & Intentions Select your top 3 values from the drop down and confirm whether or not this offer "checks the box"
D33: Reporting to: | E33: VP, Marketing | L33: Reporting to: | M33: CMO
D34: Start Date: | E34: 44044 | L34: Start Date: | M34: 44044
D36: Additional Terms | G36: Autonomy | H36: =vlookup(G36,'Data Validation'!A:B,2,0) -> Individual Contributor Independence | I36: FALSE | L36: Additional Terms | O36: =G36 -> Autonomy | P36: =H36 -> Individual Contributor Independence | Q36: FALSE
D37: =IFERROR(__xludf.DUMMYFUNCTION("IFERROR(FILTER(INDEX(offer_01_terms,0,2),INDEX(offer_01_terms,0,1)),"""")"),"Non-Compete") -> Non-Compete | L37: =IFERROR(__xludf.DUMMYFUNCTION("IFERROR(FILTER(INDEX(offer_02_terms,0,2),INDEX(offer_02_terms,0,1)),"""")"),"Non-Compete") -> Non-Compete
D38: =IFERROR(__xludf.DUMMYFUNCTION("""COMPUTED_VALUE"""),"Intellectual Property") -> Intellectual Property | L38: =IFERROR(__xludf.DUMMYFUNCTION("""COMPUTED_VALUE"""),"Severance") -> Severance
G39: Creativity | H39: =vlookup(G39,'Data Validation'!A:B,2,0) -> Designing Creating Building | I39: FALSE | O39: Creativity | P39: =H39 -> Designing Creating Building | Q39: FALSE
G42: Team | H42: =vlookup(G42,'Data Validation'!A:B,2,0) -> Collaboration Community Colleagues | I42: FALSE | O42: =G42 -> Team | P42: =H42 -> Collaboration Community Colleagues | Q42: FALSE
B46: BENEFITS | D46: Variable | E46: Equity | G46: Benefits Level 1 | H46: Benefits Level 2 | L46: Variable | M46: Equity | O46: Benefits Level 1 | P46: Benefits Level 2
D47: =IFERROR(__xludf.DUMMYFUNCTION("IFERROR(FILTER(INDEX(offer_01_benefits_variable,0,2),INDEX(offer_01_benefits_variable,0,1)),"""")"),"Commission") -> Commission | E47: =IFERROR(__xludf.DUMMYFUNCTION("IFERROR(FILTER(INDEX(offer_01_benefits_equity,0,2),INDEX(offer_01_benefits_equity,0,1)),"""")"),"Options") -> Options | G47: =IFERROR(__xludf.DUMMYFUNCTION("IFERROR(FILTER(INDEX(offer_01_benefits_level_01,0,2),INDEX(offer_01_benefits_level_01,0,1)),"""")"),"Health Insurance") -> Health Insurance | H47: =IFERROR(__xludf.DUMMYFUNCTION("IFERROR(FILTER(INDEX(offer_01_benefits_level_02,0,2),INDEX(offer_01_benefits_level_02,0,1)),"""")"),"Work From Home") -> Work From Home | L47: =IFERROR(__xludf.DUMMYFUNCTION("IFERROR(FILTER(INDEX(offer_02_benefits_variable,0,2),INDEX(offer_02_benefits_variable,0,1)),"""")"),"Commission") -> Commission | M47: =IFERROR(__xludf.DUMMYFUNCTION("IFERROR(FILTER(INDEX(offer_02_benefits_equity,0,2),INDEX(offer_02_benefits_equity,0,1)),"""")"),"Stock") -> Stock | O47: =IFERROR(__xludf.DUMMYFUNCTION("IFERROR(FILTER(INDEX(offer_02_benefits_level_01,0,2),INDEX(offer_02_benefits_level_01,0,1)),"""")"),"Health Insurance") -> Health Insurance | P47: =IFERROR(__xludf.DUMMYFUNCTION("IFERROR(FILTER(INDEX(offer_02_benefits_level_02,0,2),INDEX(offer_02_benefits_level_02,0,1)),"""")"),"Meals") -> Meals
D48: =IFERROR(__xludf.DUMMYFUNCTION("""COMPUTED_VALUE"""),"Hiring Bonus") -> Hiring Bonus | G48: =IFERROR(__xludf.DUMMYFUNCTION("""COMPUTED_VALUE"""),"Dental Insurance") -> Dental Insurance | H48: =IFERROR(__xludf.DUMMYFUNCTION("""COMPUTED_VALUE"""),"Modified Hours") -> Modified Hours | O48: =IFERROR(__xludf.DUMMYFUNCTION("""COMPUTED_VALUE"""),"Life Insurance") -> Life Insurance | P48: =IFERROR(__xludf.DUMMYFUNCTION("""COMPUTED_VALUE"""),"Cell Phone Reimbursement") -> Cell Phone Reimbursement
D49: =IFERROR(__xludf.DUMMYFUNCTION("""COMPUTED_VALUE"""),"Other Example") -> Other Example | G49: =IFERROR(__xludf.DUMMYFUNCTION("""COMPUTED_VALUE"""),"Vision Insurance") -> Vision Insurance | H49: =IFERROR(__xludf.DUMMYFUNCTION("""COMPUTED_VALUE"""),"Gym Membership") -> Gym Membership | O49: =IFERROR(__xludf.DUMMYFUNCTION("""COMPUTED_VALUE"""),"401K") -> 401K | P49: =IFERROR(__xludf.DUMMYFUNCTION("""COMPUTED_VALUE"""),"Software Training") -> Software Training
G50: =IFERROR(__xludf.DUMMYFUNCTION("""COMPUTED_VALUE"""),"401K") -> 401K | H50: =IFERROR(__xludf.DUMMYFUNCTION("""COMPUTED_VALUE"""),"Sabaticals") -> Sabaticals | O50: =IFERROR(__xludf.DUMMYFUNCTION("""COMPUTED_VALUE"""),"Sick PTO") -> Sick PTO
G51: =IFERROR(__xludf.DUMMYFUNCTION("""COMPUTED_VALUE"""),"Sick PTO") -> Sick PTO | H51: =IFERROR(__xludf.DUMMYFUNCTION("""COMPUTED_VALUE"""),"Certifications") -> Certifications | O51: =IFERROR(__xludf.DUMMYFUNCTION("""COMPUTED_VALUE"""),"Parental Leave") -> Parental Leave
G52: =IFERROR(__xludf.DUMMYFUNCTION("""COMPUTED_VALUE"""),"Parental Leave") -> Parental Leave | H52: =IFERROR(__xludf.DUMMYFUNCTION("""COMPUTED_VALUE"""),"HSA / FSA") -> HSA / FSA

Sheet Data Validation
A1: Values | B1: Desciptors
A2: Autonomy | B2: Individual Contributor Independence
A3: Balance | B3: Hours Flexibility Leisure Family
A4: Creativity | B4: Designing Creating Building
A5: Growth | B5: Challenge Advancement
A6: Impact | B6: Mission Driven Helping Society
A7: Income | B7: Salary Benefits Equity
A8: Leadership | B8: Management Influence Power
A9: Learning | B9: Soft Skills Hard Skills Knowledge
A10: Security | B10: Job Market Industry In Demand Skills
A11: Team | B11: Collaboration Community Colleagues
